Orange3_Explain-0.6.10-py3.11-nspkg.pth
Orange3_Explain-0.6.10.data/data/help/orange3-explain/.buildinfo
Orange3_Explain-0.6.10.data/data/help/orange3-explain/genindex.html
Orange3_Explain-0.6.10.data/data/help/orange3-explain/index.html
Orange3_Explain-0.6.10.data/data/help/orange3-explain/objects.inv
Orange3_Explain-0.6.10.data/data/help/orange3-explain/search.html
Orange3_Explain-0.6.10.data/data/help/orange3-explain/searchindex.js
Orange3_Explain-0.6.10.data/data/help/orange3-explain/_images/Explain-Model-Example.png
Orange3_Explain-0.6.10.data/data/help/orange3-explain/_images/Explain-Model.png
Orange3_Explain-0.6.10.data/data/help/orange3-explain/_images/Explain-Prediction-Example.png
Orange3_Explain-0.6.10.data/data/help/orange3-explain/_images/Explain-Prediction.png
Orange3_Explain-0.6.10.data/data/help/orange3-explain/_images/ICE-example.png
Orange3_Explain-0.6.10.data/data/help/orange3-explain/_images/ICE.png
Orange3_Explain-0.6.10.data/data/help/orange3-explain/_images/Permutation-Importance-Example.png
Orange3_Explain-0.6.10.data/data/help/orange3-explain/_images/Permutation-Importance.png
Orange3_Explain-0.6.10.data/data/help/orange3-explain/_sources/index.rst.txt
Orange3_Explain-0.6.10.data/data/help/orange3-explain/_sources/widgets/explain-model.md.txt
Orange3_Explain-0.6.10.data/data/help/orange3-explain/_sources/widgets/explain-prediction.md.txt
Orange3_Explain-0.6.10.data/data/help/orange3-explain/_sources/widgets/explain-predictions.md.txt
Orange3_Explain-0.6.10.data/data/help/orange3-explain/_sources/widgets/ice.md.txt
Orange3_Explain-0.6.10.data/data/help/orange3-explain/_sources/widgets/permutation-importance.md.txt
Orange3_Explain-0.6.10.data/data/help/orange3-explain/_static/basic.css
Orange3_Explain-0.6.10.data/data/help/orange3-explain/_static/custom.css
Orange3_Explain-0.6.10.data/data/help/orange3-explain/_static/doctools.js
Orange3_Explain-0.6.10.data/data/help/orange3-explain/_static/documentation_options.js
Orange3_Explain-0.6.10.dist-info/LICENSE.txt
Orange3_Explain-0.6.10.dist-info/METADATA
Orange3_Explain-0.6.10.dist-info/WHEEL
Orange3_Explain-0.6.10.dist-info/entry_points.txt
Orange3_Explain-0.6.10.dist-info/namespace_packages.txt
Orange3_Explain-0.6.10.dist-info/top_level.txt
Orange3_Explain-0.6.10.dist-info/RECORD
